napari_brainreg_standard/__init__.py
napari_brainreg_standard/_version.py
napari_brainreg_standard/brainreg_standard.py
tests/__init__.py
tests/test_brainreg_standard.py
napari_brainreg_standard-0.0.3.dist-info/LICENSE
napari_brainreg_standard-0.0.3.dist-info/METADATA
napari_brainreg_standard-0.0.3.dist-info/WHEEL
napari_brainreg_standard-0.0.3.dist-info/entry_points.txt
napari_brainreg_standard-0.0.3.dist-info/top_level.txt
napari_brainreg_standard-0.0.3.dist-info/RECORD
